Metadata-Version: 1.0
Name: syncpy
Version: 0.1
Summary: The funniest joke in the world
Home-page: http://github.com/storborg/funniest
Author: wail
Author-email: elbaniwail@gmail.com
License: MIT
Platform: UNKNOWN
